altbuf/__init__.py
altbuf-1.0.2.dist-info/LICENSE
altbuf-1.0.2.dist-info/METADATA
altbuf-1.0.2.dist-info/WHEEL
altbuf-1.0.2.dist-info/top_level.txt
altbuf-1.0.2.dist-info/RECORD
