Metadata-Version: 2.1
Name: altbuf
Version: 1.0.2
Summary: Tiny package to enter and exit the alternate buffer using ANSI escape sequences.
Home-page: https://github.com/larshb/altbuf
Author: Lars Henrik Bolstad
Author-email: lahebo@gmail.com
License: UNKNOWN
Project-URL: Bug Tracker, https://github.com/larshb/altbuf/issues
Platform: UNKNOWN
Classifier: Programming Language :: Python :: 3
Classifier: License :: OSI Approved :: MIT License
Classifier: Operating System :: OS Independent
Requires-Python: >=2.0
License-File: LICENSE
